
[
    
    {"partidoId": 1, "equipoLocal": "Banfield", "equipoVisitante": "Defensa y Justicia", "golesLocal": "", "golesVisitante": ""},
    {"partidoId": 2, "equipoLocal": "Quilmes", "equipoVisitante": "Arsenal de Sarandi", "golesLocal": "", "golesVisitante": ""},
    {"partidoId": 3, "equipoLocal": "Deportivo Moron", "equipoVisitante": "Patronato", "golesLocal": "", "golesVisitante": ""},
    {"partidoId": 4, "equipoLocal": "Central Cordoba", "equipoVisitante": "Atlanta", "golesLocal": "", "golesVisitante": ""}
]